wfs_trx/__init__.py
wfs_trx/py.typed
wfs_trx/schema_builder.py
wfs_trx/trx.py
wfs_trx/version.py
wfs_trx-0.0.3.dist-info/METADATA
wfs_trx-0.0.3.dist-info/WHEEL
wfs_trx-0.0.3.dist-info/top_level.txt
wfs_trx-0.0.3.dist-info/RECORD
